Workbook

Sheet START HERE
B2: WELCOME TO YOUR PREMIUM WEDDING PLANNER
B3: A calm, elegant system for planning every detail of your wedding — from budget to seating chart.
B6: HOW THIS WORKBOOK WORKS
B7: 1. Start on the Settings sheet — enter your names, wedding date, budget and guest target once.
B8: 2. Every other sheet (Dashboard, Budget, Guest List, Checklist and more) calculates automatically from what you enter.
B9: 3. Use the dropdown menus in colored-header columns to keep your data consistent — just click a cell and choose from the list.
B10: 4. Visit the Dashboard any time for a beautiful, real-time snapshot of your whole wedding.
B11: 5. Each sheet has a small navigation link at the top-left to jump back to the Dashboard or this page.
B12: 6. All key sheets are print-ready — use File > Print, and each will fit neatly on the page.
B14: WHAT'S INSIDE
B15: Dashboard | D15: Your wedding at a glance — budget, guests, checklist and more.
B16: Budget | D16: Track every planned and actual expense by category.
B17: Vendors | D17: Contact details, quotes and contracts for every vendor.
B18: Guest List | D18: Manage invitations, RSVPs and meal preferences.
B19: Seating Plan | D19: Assign guests to tables, synced with your Guest List.
B20: Timeline | D20: Minute-by-minute plan for the wedding day.
B21: Master Checklist | D21: Every planning task, organized by timeframe.
B22: Payments | D22: Every deposit, balance and due date.
B23: Wedding Party | D23: Roles and responsibilities for your closest circle.
B24: Venue Comparison | D24: Compare every venue you're considering.
B25: Food & Drinks | D25: Plan your menu and catering costs.
B26: Honeymoon Budget | D26: Plan and track your post-wedding getaway.
... B30: Settings | D30: Your wedding details, budget and dropdown lists.

Sheet Dashboard
B1: ‹ Start Here
B2: OUR WEDDING | Q2: =IF(WeddingDate="","—",IF(WeddingDate>=TODAY(),WeddingDate-TODAY()&" DAYS TO GO",TEXT(WeddingDate,"d mmm yyyy")&" ❦ Married!")) -> —
B3: =IF(Partner1Name="","Partner One",Partner1Name)&" & "&IF(Partner2Name="","Partner Two",Partner2Name) -> Partner One & Partner Two
B4: =IF(WeddingDate="","Wedding date not yet set",TEXT(WeddingDate,"dddd, d mmmm yyyy")) -> Wedding date not yet set
B7: FINANCIAL SNAPSHOT
B8: =TotalBudget -> 0 | F8: =SUM(Budget!G6:G35) -> 0 | J8: =IF(TotalBudget="","",TotalBudget-SUM(Budget!G6:G35)) | N8: =SUM(Budget!J6:J35) -> 0 | R8: =SUM(Budget!K6:K35) -> 0
B10: TOTAL BUDGET | F10: ACTUAL SPENDING | J10: REMAINING BUDGET | N10: AMOUNT PAID | R10: OUTSTANDING
B12: GUEST SNAPSHOT
B13: =COUNTA('Guest List'!B6:B65) -> 0 | F13: =COUNTIF('Guest List'!I6:I65,"Attending") -> 0 | J13: =COUNTIF('Guest List'!I6:I65,"Pending") -> 0 | N13: =COUNTIF('Guest List'!I6:I65,"Declined") -> 0 | R13: =COUNTA(Vendors!B6:B31) -> 0
B15: TOTAL GUESTS | F15: CONFIRMED | J15: PENDING RSVPS | N15: NOT ATTENDING | R15: VENDORS BOOKED
B17: PLANNING PROGRESS & HONEYMOON
B18: =IFERROR(COUNTIF('Master Checklist'!H6:H65,"Completed")/(COUNTA('Master Checklist'!C6:C65)),"") | F18: =COUNTIFS('Master Checklist'!C6:C65,"<>",'Master Checklist'!H6:H65,"<>Completed") -> 0 | J18: =SUM(Vendors!K6:K31) -> 0 | N18: =HoneymoonBudgetSetting -> 0 | R18: =SUM('Honeymoon Budget'!G6:G15) -> 0
B20: CHECKLIST COMPLETE | F20: TASKS REMAINING | J20: OUTSTANDING VENDOR PMTS | N20: HONEYMOON BUDGET | R20: HONEYMOON REMAINING
B22: ATTENTION NEEDED
B23: =COUNTIFS(Payments!H6:H29,"<>",Payments!H6:H29,"<"&TODAY(),Payments!I6:I29,"<>Paid in Full") -> 0 | F23: =COUNTIF('Guest List'!I6:I65,"Pending") -> 0 | J23: =COUNTIFS('Master Checklist'!G6:G65,"<>",'Master Checklist'!G6:G65,"<"&TODAY(),'Master Checklist'!H6:H65,"<>Completed") -> 0 | N23: =SUMPRODUCT((Lists!$X$2:$X$21>Lists!$W$2:$W$21)*1) -> 0
B25: OVERDUE PAYMENTS | F25: PENDING RSVPS | J25: OVERDUE TASKS | N25: OVER-BUDGET CATEGORIES

Sheet Budget
B1: ‹ Dashboard | C1: ‹ Start Here
B2: BUDGET & EXPENSES
B3: Track your wedding spending and stay within your plan.
B5: Category | C5: Subcategory | D5: Item / Description | E5: Vendor | F5: Planned Budget | G5: Actual Cost | H5: Difference | I5: Deposit | J5: Amount Paid | K5: Amount Remaining | L5: Due Date | M5: Payment Status | N5: Notes
H6: =IF(F6="","",F6-G6) | K6: =IF(G6="","",G6-J6)
H7: =IF(F7="","",F7-G7) | K7: =IF(G7="","",G7-J7)
H8: =IF(F8="","",F8-G8) | K8: =IF(G8="","",G8-J8)
H9: =IF(F9="","",F9-G9) | K9: =IF(G9="","",G9-J9)
H10: =IF(F10="","",F10-G10) | K10: =IF(G10="","",G10-J10)
H11: =IF(F11="","",F11-G11) | K11: =IF(G11="","",G11-J11)
H12: =IF(F12="","",F12-G12) | K12: =IF(G12="","",G12-J12)
H13: =IF(F13="","",F13-G13) | K13: =IF(G13="","",G13-J13)
H14: =IF(F14="","",F14-G14) | K14: =IF(G14="","",G14-J14)
H15: =IF(F15="","",F15-G15) | K15: =IF(G15="","",G15-J15)
H16: =IF(F16="","",F16-G16) | K16: =IF(G16="","",G16-J16)
H17: =IF(F17="","",F17-G17) | K17: =IF(G17="","",G17-J17)
... H35: =IF(F35="","",F35-G35) | K35: =IF(G35="","",G35-J35)
B37: BUDGET SUMMARY
B38: =SUM(F6:F35) -> 0 | E38: =SUM(G6:G35) -> 0 | H38: =SUM(K6:K35) -> 0 | K38: =IFERROR(SUM(G6:G35)/TotalBudget,"")
B40: TOTAL PLANNED | E40: TOTAL ACTUAL | H40: TOTAL REMAINING | K40: BUDGET USED

Sheet Vendors
B1: ‹ Dashboard | C1: ‹ Start Here
B2: VENDOR DIRECTORY
B3: Every vendor, quote and contract in one elegant place.
B5: Vendor Name | C5: Category | D5: Contact Person | E5: Phone | F5: Email | G5: Website | H5: Quote | I5: Final Cost | J5: Deposit | K5: Remaining | L5: Contract Status | M5: Payment Status | N5: Due Date | O5: Rating | P5: Notes
K6: =IF(I6="","",I6-J6)
K7: =IF(I7="","",I7-J7)
K8: =IF(I8="","",I8-J8)
K9: =IF(I9="","",I9-J9)
K10: =IF(I10="","",I10-J10)
K11: =IF(I11="","",I11-J11)
K12: =IF(I12="","",I12-J12)
K13: =IF(I13="","",I13-J13)
K14: =IF(I14="","",I14-J14)
K15: =IF(I15="","",I15-J15)
K16: =IF(I16="","",I16-J16)
K17: =IF(I17="","",I17-J17)
... K31: =IF(I31="","",I31-J31)
B33: VENDOR SUMMARY
B34: =COUNTA(B6:B31) -> 0 | E34: =COUNTIF(L6:L31,"Signed") -> 0 | H34: =SUM(K6:K31) -> 0 | K34: =COUNTIF(M6:M31,"Overdue") -> 0
B36: TOTAL VENDORS | E36: CONTRACTS SIGNED | H36: OUTSTANDING BALANCE | K36: OVERDUE PAYMENTS

Sheet Guest List
B1: ‹ Dashboard | C1: ‹ Start Here
B2: GUEST LIST & RSVP
B3: Manage every invitee, RSVP and meal preference.
B5: Guest Name | C5: Household / Group | D5: Side | E5: Relationship | F5: Email | G5: Phone | H5: Invitation Sent | I5: RSVP Status | J5: Plus One | K5: Plus One Name | L5: Meal Preference | M5: Dietary Restrictions | N5: Children Attending | O5: Table Number | P5: Notes
B67: GUEST SUMMARY
B68: =COUNTA(B6:B65) -> 0 | E68: =COUNTIF(I6:I65,"Attending")+COUNTIFS(I6:I65,"Attending",J6:J65,"Yes") -> 0 | H68: =COUNTIF(I6:I65,"Pending") -> 0 | K68: =COUNTIF(I6:I65,"Declined") -> 0
B70: TOTAL INVITED | E70: ATTENDING | H70: PENDING | K70: DECLINED

Sheet Seating Plan
B1: ‹ Dashboard | C1: ‹ Start Here
B2: SEATING PLAN
B3: Assign every guest to a table — synced automatically with your Guest List.
B5: TABLE OVERVIEW
B6: Table # | C6: Capacity | D6: Seated | E6: Seats Remaining | H6: Table # | I6: Capacity | J6: Seated | K6: Seats Remaining
B7: 1 | C7: =IF(B7<=TableCount,SeatsPerTable,"") -> 10 | D7: =IF(C7="","",COUNTIF(GuestTable[Table Number],B7)) -> 0 | E7: =IF(C7="","",C7-D7) -> 10 | H7: 11 | I7: =IF(H7<=TableCount,SeatsPerTable,"") -> 10 | J7: =IF(I7="","",COUNTIF(GuestTable[Table Number],H7)) -> 0 | K7: =IF(I7="","",I7-J7) -> 10
B8: 2 | C8: =IF(B8<=TableCount,SeatsPerTable,"") -> 10 | D8: =IF(C8="","",COUNTIF(GuestTable[Table Number],B8)) -> 0 | E8: =IF(C8="","",C8-D8) -> 10 | H8: 12 | I8: =IF(H8<=TableCount,SeatsPerTable,"") -> 10 | J8: =IF(I8="","",COUNTIF(GuestTable[Table Number],H8)) -> 0 | K8: =IF(I8="","",I8-J8) -> 10
B9: 3 | C9: =IF(B9<=TableCount,SeatsPerTable,"") -> 10 | D9: =IF(C9="","",COUNTIF(GuestTable[Table Number],B9)) -> 0 | E9: =IF(C9="","",C9-D9) -> 10 | H9: 13 | I9: =IF(H9<=TableCount,SeatsPerTable,"") -> 10 | J9: =IF(I9="","",COUNTIF(GuestTable[Table Number],H9)) -> 0 | K9: =IF(I9="","",I9-J9) -> 10
B10: 4 | C10: =IF(B10<=TableCount,SeatsPerTable,"") -> 10 | D10: =IF(C10="","",COUNTIF(GuestTable[Table Number],B10)) -> 0 | E10: =IF(C10="","",C10-D10) -> 10 | H10: 14 | I10: =IF(H10<=TableCount,SeatsPerTable,"") -> 10 | J10: =IF(I10="","",COUNTIF(GuestTable[Table Number],H10)) -> 0 | K10: =IF(I10="","",I10-J10) -> 10
B11: 5 | C11: =IF(B11<=TableCount,SeatsPerTable,"") -> 10 | D11: =IF(C11="","",COUNTIF(GuestTable[Table Number],B11)) -> 0 | E11: =IF(C11="","",C11-D11) -> 10 | H11: 15 | I11: =IF(H11<=TableCount,SeatsPerTable,"") -> 10 | J11: =IF(I11="","",COUNTIF(GuestTable[Table Number],H11)) -> 0 | K11: =IF(I11="","",I11-J11) -> 10
B12: 6 | C12: =IF(B12<=TableCount,SeatsPerTable,"") -> 10 | D12: =IF(C12="","",COUNTIF(GuestTable[Table Number],B12)) -> 0 | E12: =IF(C12="","",C12-D12) -> 10 | H12: 16 | I12: =IF(H12<=TableCount,SeatsPerTable,"") -> 10 | J12: =IF(I12="","",COUNTIF(GuestTable[Table Number],H12)) -> 0 | K12: =IF(I12="","",I12-J12) -> 10
B13: 7 | C13: =IF(B13<=TableCount,SeatsPerTable,"") -> 10 | D13: =IF(C13="","",COUNTIF(GuestTable[Table Number],B13)) -> 0 | E13: =IF(C13="","",C13-D13) -> 10 | H13: 17 | I13: =IF(H13<=TableCount,SeatsPerTable,"") | J13: =IF(I13="","",COUNTIF(GuestTable[Table Number],H13)) | K13: =IF(I13="","",I13-J13)
B14: 8 | C14: =IF(B14<=TableCount,SeatsPerTable,"") -> 10 | D14: =IF(C14="","",COUNTIF(GuestTable[Table Number],B14)) -> 0 | E14: =IF(C14="","",C14-D14) -> 10 | H14: 18 | I14: =IF(H14<=TableCount,SeatsPerTable,"") | J14: =IF(I14="","",COUNTIF(GuestTable[Table Number],H14)) | K14: =IF(I14="","",I14-J14)
B15: 9 | C15: =IF(B15<=TableCount,SeatsPerTable,"") -> 10 | D15: =IF(C15="","",COUNTIF(GuestTable[Table Number],B15)) -> 0 | E15: =IF(C15="","",C15-D15) -> 10 | H15: 19 | I15: =IF(H15<=TableCount,SeatsPerTable,"") | J15: =IF(I15="","",COUNTIF(GuestTable[Table Number],H15)) | K15: =IF(I15="","",I15-J15)
B16: 10 | C16: =IF(B16<=TableCount,SeatsPerTable,"") -> 10 | D16: =IF(C16="","",COUNTIF(GuestTable[Table Number],B16)) -> 0 | E16: =IF(C16="","",C16-D16) -> 10 | H16: 20 | I16: =IF(H16<=TableCount,SeatsPerTable,"") | J16: =IF(I16="","",COUNTIF(GuestTable[Table Number],H16)) | K16: =IF(I16="","",I16-J16)
B19: GUEST ROSTER
B20: Table Number | C20: Guest Name | D20: Household | E20: Meal | F20: Special Requirements | G20: Notes
B21: =IF('Guest List'!O6="","",'Guest List'!O6) | C21: =IF('Guest List'!B6="","",'Guest List'!B6) | D21: =IF('Guest List'!C6="","",'Guest List'!C6) | E21: =IF('Guest List'!L6="","",'Guest List'!L6)
B22: =IF('Guest List'!O7="","",'Guest List'!O7) | C22: =IF('Guest List'!B7="","",'Guest List'!B7) | D22: =IF('Guest List'!C7="","",'Guest List'!C7) | E22: =IF('Guest List'!L7="","",'Guest List'!L7)
B23: =IF('Guest List'!O8="","",'Guest List'!O8) | C23: =IF('Guest List'!B8="","",'Guest List'!B8) | D23: =IF('Guest List'!C8="","",'Guest List'!C8) | E23: =IF('Guest List'!L8="","",'Guest List'!L8)
B24: =IF('Guest List'!O9="","",'Guest List'!O9) | C24: =IF('Guest List'!B9="","",'Guest List'!B9) | D24: =IF('Guest List'!C9="","",'Guest List'!C9) | E24: =IF('Guest List'!L9="","",'Guest List'!L9)
B25: =IF('Guest List'!O10="","",'Guest List'!O10) | C25: =IF('Guest List'!B10="","",'Guest List'!B10) | D25: =IF('Guest List'!C10="","",'Guest List'!C10) | E25: =IF('Guest List'!L10="","",'Guest List'!L10)
B26: =IF('Guest List'!O11="","",'Guest List'!O11) | C26: =IF('Guest List'!B11="","",'Guest List'!B11) | D26: =IF('Guest List'!C11="","",'Guest List'!C11) | E26: =IF('Guest List'!L11="","",'Guest List'!L11)
B27: =IF('Guest List'!O12="","",'Guest List'!O12) | C27: =IF('Guest List'!B12="","",'Guest List'!B12) | D27: =IF('Guest List'!C12="","",'Guest List'!C12) | E27: =IF('Guest List'!L12="","",'Guest List'!L12)
B28: =IF('Guest List'!O13="","",'Guest List'!O13) | C28: =IF('Guest List'!B13="","",'Guest List'!B13) | D28: =IF('Guest List'!C13="","",'Guest List'!C13) | E28: =IF('Guest List'!L13="","",'Guest List'!L13)
B29: =IF('Guest List'!O14="","",'Guest List'!O14) | C29: =IF('Guest List'!B14="","",'Guest List'!B14) | D29: =IF('Guest List'!C14="","",'Guest List'!C14) | E29: =IF('Guest List'!L14="","",'Guest List'!L14)
B30: =IF('Guest List'!O15="","",'Guest List'!O15) | C30: =IF('Guest List'!B15="","",'Guest List'!B15) | D30: =IF('Guest List'!C15="","",'Guest List'!C15) | E30: =IF('Guest List'!L15="","",'Guest List'!L15)
B31: =IF('Guest List'!O16="","",'Guest List'!O16) | C31: =IF('Guest List'!B16="","",'Guest List'!B16) | D31: =IF('Guest List'!C16="","",'Guest List'!C16) | E31: =IF('Guest List'!L16="","",'Guest List'!L16)
B32: =IF('Guest List'!O17="","",'Guest List'!O17) | C32: =IF('Guest List'!B17="","",'Guest List'!B17) | D32: =IF('Guest List'!C17="","",'Guest List'!C17) | E32: =IF('Guest List'!L17="","",'Guest List'!L17)
... B80: =IF('Guest List'!O65="","",'Guest List'!O65) | C80: =IF('Guest List'!B65="","",'Guest List'!B65) | D80: =IF('Guest List'!C65="","",'Guest List'!C65) | E80: =IF('Guest List'!L65="","",'Guest List'!L65)

Sheet Timeline
B1: ‹ Dashboard | C1: ‹ Start Here
B2: WEDDING DAY TIMELINE
B3: Minute-by-minute plan for the big day.
B5: Time | C5: Event | D5: Location | E5: Person Responsible | F5: Vendor | G5: Notes

Sheet Master Checklist
B1: ‹ Dashboard | C1: ‹ Start Here
B2: MASTER CHECKLIST
B3: Every planning task, organized by timeline.
B5: Period | C5: Task | D5: Category | E5: Priority | F5: Owner | G5: Due Date | H5: Status | I5: Notes
B67: CHECKLIST SUMMARY
B68: =COUNTA(C6:C65) -> 0 | E68: =COUNTIF(H6:H65,"Completed") -> 0 | H68: =COUNTIFS(C6:C65,"<>",H6:H65,"<>Completed") -> 0 | K68: =IFERROR(COUNTIF(H6:H65,"Completed")/(COUNTA(C6:C65)),"")
B70: TOTAL TASKS | E70: COMPLETED | H70: REMAINING | K70: COMPLETION %

Sheet Payments
B1: ‹ Dashboard | C1: ‹ Start Here
B2: PAYMENT SCHEDULE
B3: Every deposit, balance and due date, tracked automatically.
B5: Vendor | C5: Expense | D5: Total Cost | E5: Deposit | F5: Amount Paid | G5: Remaining | H5: Due Date | I5: Payment Status | J5: Payment Method | K5: Notes
G6: =IF(D6="","",D6-(E6+F6))
G7: =IF(D7="","",D7-(E7+F7))
G8: =IF(D8="","",D8-(E8+F8))
G9: =IF(D9="","",D9-(E9+F9))
G10: =IF(D10="","",D10-(E10+F10))
G11: =IF(D11="","",D11-(E11+F11))
G12: =IF(D12="","",D12-(E12+F12))
G13: =IF(D13="","",D13-(E13+F13))
G14: =IF(D14="","",D14-(E14+F14))
G15: =IF(D15="","",D15-(E15+F15))
G16: =IF(D16="","",D16-(E16+F16))
G17: =IF(D17="","",D17-(E17+F17))
... G29: =IF(D29="","",D29-(E29+F29))
B31: PAYMENTS SUMMARY
B32: =SUM(D6:D29) -> 0 | E32: =SUM(E6:E29)+SUM(F6:F29) -> 0 | H32: =SUM(G6:G29) -> 0 | K32: =COUNTIFS(H6:H29,"<"&TODAY(),I6:I29,"<>Paid in Full") -> 0
B34: TOTAL PAYABLE | E34: TOTAL PAID | H34: TOTAL REMAINING | K34: OVERDUE

Sheet Wedding Party
B1: ‹ Dashboard | C1: ‹ Start Here
B2: WEDDING PARTY
B3: Roles, responsibilities and attire for your closest circle.
B5: Name | C5: Role | D5: Side | E5: Phone | F5: Email | G5: Responsibilities | H5: Attire | I5: Notes

Sheet Venue Comparison
B1: ‹ Dashboard | C1: ‹ Start Here
B2: VENUE COMPARISON
B3: Compare every venue you toured, side by side.
B5: Venue | C5: Location | D5: Capacity | E5: Rental Cost | F5: Catering Cost | G5: Deposit | H5: Availability | I5: Ceremony Included | J5: Reception Included | K5: Parking | L5: Accommodation | M5: Rating | N5: Notes

Sheet Food & Drinks
B1: ‹ Dashboard | C1: ‹ Start Here
B2: FOOD & DRINKS
B3: Plan your menu, portions and per-guest cost.
B5: Catering Vendor | C5: Menu Item | D5: Category | E5: Quantity | F5: Price | G5: Total | H5: Dietary Notes | I5: Notes
G6: =IF(E6="","",E6*F6)
G7: =IF(E7="","",E7*F7)
G8: =IF(E8="","",E8*F8)
G9: =IF(E9="","",E9*F9)
G10: =IF(E10="","",E10*F10)
G11: =IF(E11="","",E11*F11)
G12: =IF(E12="","",E12*F12)
G13: =IF(E13="","",E13*F13)
G14: =IF(E14="","",E14*F14)
G15: =IF(E15="","",E15*F15)
G16: =IF(E16="","",E16*F16)
G17: =IF(E17="","",E17*F17)
... G29: =IF(E29="","",E29*F29)
B31: MENU SUMMARY
B32: =SUM(G6:G29) -> 0
B34: TOTAL MENU COST

Sheet Honeymoon Budget
B1: ‹ Dashboard | C1: ‹ Start Here
B2: HONEYMOON BUDGET
B3: Plan and track spending for your post-wedding getaway.
B5: Category | C5: Planned Budget | D5: Actual Cost | E5: Difference | F5: Amount Paid | G5: Remaining | H5: Due Date | I5: Notes
E6: =IF(C6="","",C6-D6) | G6: =IF(D6="","",D6-F6)
E7: =IF(C7="","",C7-D7) | G7: =IF(D7="","",D7-F7)
E8: =IF(C8="","",C8-D8) | G8: =IF(D8="","",D8-F8)
E9: =IF(C9="","",C9-D9) | G9: =IF(D9="","",D9-F9)
E10: =IF(C10="","",C10-D10) | G10: =IF(D10="","",D10-F10)
E11: =IF(C11="","",C11-D11) | G11: =IF(D11="","",D11-F11)
E12: =IF(C12="","",C12-D12) | G12: =IF(D12="","",D12-F12)
E13: =IF(C13="","",C13-D13) | G13: =IF(D13="","",D13-F13)
E14: =IF(C14="","",C14-D14) | G14: =IF(D14="","",D14-F14)
E15: =IF(C15="","",C15-D15) | G15: =IF(D15="","",D15-F15)
B17: HONEYMOON SUMMARY
B18: =SUM(C6:C15) -> 0 | E18: =SUM(D6:D15) -> 0 | H18: =SUM(G6:G15) -> 0
B20: PLANNED TOTAL | E20: ACTUAL TOTAL | H20: REMAINING

Sheet Contacts
B1: ‹ Dashboard | C1: ‹ Start Here
B2: CONTACTS
B3: Every phone number and email you need, in one place.
B5: Name | C5: Company | D5: Category | E5: Role | F5: Phone | G5: Email | H5: Website | I5: Address | J5: Notes

Sheet Gift Tracker
B1: ‹ Dashboard | C1: ‹ Start Here
B2: GIFT TRACKER
B3: Track gifts received and thank-you notes sent.
B5: Guest Name | C5: Gift | D5: Gift Type | E5: Value | F5: Thank You Sent | G5: Date Received | H5: Notes
B35: GIFT SUMMARY
B36: =COUNTA(B6:B33) -> 0 | E36: =SUM(E6:E33) -> 0 | H36: =COUNTIF(F6:F33,"Yes") -> 0 | K36: =COUNTIFS(B6:B33,"<>",F6:F33,"<>Yes") -> 0
B38: GIFTS RECEIVED | E38: TOTAL VALUE | H38: THANK-YOUS SENT | K38: THANK-YOUS PENDING

Sheet Calendar
B1: ‹ Dashboard | C1: ‹ Start Here
B2: PLANNING CALENDAR
B3: Every task deadline and payment due date, gathered in one chronological view.
B5: TASK DEADLINES
B6: Due Date | C6: Task | D6: Category | E6: Status
B7: =IF('Master Checklist'!G6="","",'Master Checklist'!G6) | C7: =IF('Master Checklist'!C6="","",'Master Checklist'!C6) | D7: =IF('Master Checklist'!D6="","",'Master Checklist'!D6) | E7: =IF('Master Checklist'!H6="","",'Master Checklist'!H6)
B8: =IF('Master Checklist'!G7="","",'Master Checklist'!G7) | C8: =IF('Master Checklist'!C7="","",'Master Checklist'!C7) | D8: =IF('Master Checklist'!D7="","",'Master Checklist'!D7) | E8: =IF('Master Checklist'!H7="","",'Master Checklist'!H7)
B9: =IF('Master Checklist'!G8="","",'Master Checklist'!G8) | C9: =IF('Master Checklist'!C8="","",'Master Checklist'!C8) | D9: =IF('Master Checklist'!D8="","",'Master Checklist'!D8) | E9: =IF('Master Checklist'!H8="","",'Master Checklist'!H8)
B10: =IF('Master Checklist'!G9="","",'Master Checklist'!G9) | C10: =IF('Master Checklist'!C9="","",'Master Checklist'!C9) | D10: =IF('Master Checklist'!D9="","",'Master Checklist'!D9) | E10: =IF('Master Checklist'!H9="","",'Master Checklist'!H9)
B11: =IF('Master Checklist'!G10="","",'Master Checklist'!G10) | C11: =IF('Master Checklist'!C10="","",'Master Checklist'!C10) | D11: =IF('Master Checklist'!D10="","",'Master Checklist'!D10) | E11: =IF('Master Checklist'!H10="","",'Master Checklist'!H10)
B12: =IF('Master Checklist'!G11="","",'Master Checklist'!G11) | C12: =IF('Master Checklist'!C11="","",'Master Checklist'!C11) | D12: =IF('Master Checklist'!D11="","",'Master Checklist'!D11) | E12: =IF('Master Checklist'!H11="","",'Master Checklist'!H11)
B13: =IF('Master Checklist'!G12="","",'Master Checklist'!G12) | C13: =IF('Master Checklist'!C12="","",'Master Checklist'!C12) | D13: =IF('Master Checklist'!D12="","",'Master Checklist'!D12) | E13: =IF('Master Checklist'!H12="","",'Master Checklist'!H12)
B14: =IF('Master Checklist'!G13="","",'Master Checklist'!G13) | C14: =IF('Master Checklist'!C13="","",'Master Checklist'!C13) | D14: =IF('Master Checklist'!D13="","",'Master Checklist'!D13) | E14: =IF('Master Checklist'!H13="","",'Master Checklist'!H13)
B15: =IF('Master Checklist'!G14="","",'Master Checklist'!G14) | C15: =IF('Master Checklist'!C14="","",'Master Checklist'!C14) | D15: =IF('Master Checklist'!D14="","",'Master Checklist'!D14) | E15: =IF('Master Checklist'!H14="","",'Master Checklist'!H14)
B16: =IF('Master Checklist'!G15="","",'Master Checklist'!G15) | C16: =IF('Master Checklist'!C15="","",'Master Checklist'!C15) | D16: =IF('Master Checklist'!D15="","",'Master Checklist'!D15) | E16: =IF('Master Checklist'!H15="","",'Master Checklist'!H15)
B17: =IF('Master Checklist'!G16="","",'Master Checklist'!G16) | C17: =IF('Master Checklist'!C16="","",'Master Checklist'!C16) | D17: =IF('Master Checklist'!D16="","",'Master Checklist'!D16) | E17: =IF('Master Checklist'!H16="","",'Master Checklist'!H16)
B18: =IF('Master Checklist'!G17="","",'Master Checklist'!G17) | C18: =IF('Master Checklist'!C17="","",'Master Checklist'!C17) | D18: =IF('Master Checklist'!D17="","",'Master Checklist'!D17) | E18: =IF('Master Checklist'!H17="","",'Master Checklist'!H17)
... B66: =IF('Master Checklist'!G65="","",'Master Checklist'!G65) | C66: =IF('Master Checklist'!C65="","",'Master Checklist'!C65) | D66: =IF('Master Checklist'!D65="","",'Master Checklist'!D65) | E66: =IF('Master Checklist'!H65="","",'Master Checklist'!H65)
B69: PAYMENT DEADLINES
B70: Due Date | C70: Vendor / Expense | D70: Amount | E70: Status
B71: =IF(Payments!H6="","",Payments!H6) | C71: =IF(Payments!B6="","",Payments!B6&" - "&Payments!C6) | D71: =IF(Payments!F6="","",Payments!F6) | E71: =IF(Payments!I6="","",Payments!I6)
B72: =IF(Payments!H7="","",Payments!H7) | C72: =IF(Payments!B7="","",Payments!B7&" - "&Payments!C7) | D72: =IF(Payments!F7="","",Payments!F7) | E72: =IF(Payments!I7="","",Payments!I7)
B73: =IF(Payments!H8="","",Payments!H8) | C73: =IF(Payments!B8="","",Payments!B8&" - "&Payments!C8) | D73: =IF(Payments!F8="","",Payments!F8) | E73: =IF(Payments!I8="","",Payments!I8)
B74: =IF(Payments!H9="","",Payments!H9) | C74: =IF(Payments!B9="","",Payments!B9&" - "&Payments!C9) | D74: =IF(Payments!F9="","",Payments!F9) | E74: =IF(Payments!I9="","",Payments!I9)
B75: =IF(Payments!H10="","",Payments!H10) | C75: =IF(Payments!B10="","",Payments!B10&" - "&Payments!C10) | D75: =IF(Payments!F10="","",Payments!F10) | E75: =IF(Payments!I10="","",Payments!I10)
B76: =IF(Payments!H11="","",Payments!H11) | C76: =IF(Payments!B11="","",Payments!B11&" - "&Payments!C11) | D76: =IF(Payments!F11="","",Payments!F11) | E76: =IF(Payments!I11="","",Payments!I11)
B77: =IF(Payments!H12="","",Payments!H12) | C77: =IF(Payments!B12="","",Payments!B12&" - "&Payments!C12) | D77: =IF(Payments!F12="","",Payments!F12) | E77: =IF(Payments!I12="","",Payments!I12)
B78: =IF(Payments!H13="","",Payments!H13) | C78: =IF(Payments!B13="","",Payments!B13&" - "&Payments!C13) | D78: =IF(Payments!F13="","",Payments!F13) | E78: =IF(Payments!I13="","",Payments!I13)
B79: =IF(Payments!H14="","",Payments!H14) | C79: =IF(Payments!B14="","",Payments!B14&" - "&Payments!C14) | D79: =IF(Payments!F14="","",Payments!F14) | E79: =IF(Payments!I14="","",Payments!I14)
B80: =IF(Payments!H15="","",Payments!H15) | C80: =IF(Payments!B15="","",Payments!B15&" - "&Payments!C15) | D80: =IF(Payments!F15="","",Payments!F15) | E80: =IF(Payments!I15="","",Payments!I15)
B81: =IF(Payments!H16="","",Payments!H16) | C81: =IF(Payments!B16="","",Payments!B16&" - "&Payments!C16) | D81: =IF(Payments!F16="","",Payments!F16) | E81: =IF(Payments!I16="","",Payments!I16)
B82: =IF(Payments!H17="","",Payments!H17) | C82: =IF(Payments!B17="","",Payments!B17&" - "&Payments!C17) | D82: =IF(Payments!F17="","",Payments!F17) | E82: =IF(Payments!I17="","",Payments!I17)
... B94: =IF(Payments!H29="","",Payments!H29) | C94: =IF(Payments!B29="","",Payments!B29&" - "&Payments!C29) | D94: =IF(Payments!F29="","",Payments!F29) | E94: =IF(Payments!I29="","",Payments!I29)

Sheet Settings
B2: SETTINGS
B3: Centralize your wedding details, budget and preferences once — every other sheet updates automatically.
B6: Partner 1 Name
B7: Partner 2 Name
B8: Wedding Date
B9: Currency Symbol | C9: $
B10: Wedding Location
B11: Guest Target
B12: Total Wedding Budget
B13: Number of Tables | C13: 16
B14: Seats per Table | C14: 10
B15: Honeymoon Budget
B16: RSVP Reply-By Date
B18: Edit the values above — the Dashboard, Budget, Guest List and every other sheet reference these settings automatically.

Sheet Lists
A1: RSVPStatus | B1: PaymentStatus | C1: TaskStatus | D1: Priority | E1: ContractStatus | F1: BudgetCategory | G1: MealPreference | H1: InvitationStatus | I1: Side | J1: Owner | K1: PaymentMethod | L1: YesNo | M1: GiftType | N1: ChecklistPeriod | O1: FoodCategory | P1: HoneymoonCategory | Q1: Rating | R1: PlusOne | S1: Children | W1: Planned | X1: Actual | AE1: Completed | AF1: Remaining
A2: Pending | B2: Not Started | C2: Not Started | D2: Low | E2: Not Sent | F2: Venue | G2: Standard | H2: Not Sent | I2: Partner 1 | J2: Partner 1 | K2: Bank Transfer | L2: Yes | M2: Physical Gift | N2: 12+ Months Before | O2: Appetizers | P2: Flights | Q2: 1 | R2: Yes | S2: Yes | W2: =SUMIF(Budget!$B$6:$B$35,Lists!F2,Budget!$F$6:$F$35) -> 0 | X2: =SUMIF(Budget!$B$6:$B$35,Lists!F2,Budget!$G$6:$G$35) -> 0 | Y2: Paid | Z2: =SUM(Budget!J6:J35) -> 0 | AA2: =IFERROR(LARGE(Budget!$G$6:$G$35,1),"") | AB2: =IFERROR(INDEX(Budget!$D$6:$D$35,MATCH(AA2,Budget!$G$6:$G$35,0)),"") | AC2: =COUNTIF('Guest List'!$I$6:$I$65,Lists!A2) -> 0 | AD2: =COUNTIF('Guest List'!$L$6:$L$65,Lists!G2) -> 0 | AE2: =COUNTIFS('Master Checklist'!$B$6:$B$65,Lists!N2,'Master Checklist'!$H$6:$H$65,"Completed") -> 0 | AF2: =COUNTIFS('Master Checklist'!$B$6:$B$65,Lists!N2)-AE2 -> 0 | AG2: 12+ Months
A3: Attending | B3: Deposit Paid | C3: In Progress | D3: Medium | E3: Sent | F3: Catering | G3: Vegetarian | H3: Save-the-Date Sent | I3: Partner 2 | J3: Partner 2 | K3: Credit Card | L3: No | M3: Cash Gift | N3: 9-12 Months Before | O3: Main Course | P3: Hotel | Q3: 2 | R3: No | S3: No | W3: =SUMIF(Budget!$B$6:$B$35,Lists!F3,Budget!$F$6:$F$35) -> 0 | X3: =SUMIF(Budget!$B$6:$B$35,Lists!F3,Budget!$G$6:$G$35) -> 0 | Y3: Remaining | Z3: =SUM(Budget!K6:K35) -> 0 | AA3: =IFERROR(LARGE(Budget!$G$6:$G$35,2),"") | AB3: =IFERROR(INDEX(Budget!$D$6:$D$35,MATCH(AA3,Budget!$G$6:$G$35,0)),"") | AC3: =COUNTIF('Guest List'!$I$6:$I$65,Lists!A3) -> 0 | AD3: =COUNTIF('Guest List'!$L$6:$L$65,Lists!G3) -> 0 | AE3: =COUNTIFS('Master Checklist'!$B$6:$B$65,Lists!N3,'Master Checklist'!$H$6:$H$65,"Completed") -> 0 | AF3: =COUNTIFS('Master Checklist'!$B$6:$B$65,Lists!N3)-AE3 -> 0 | AG3: 9-12 Months
A4: Declined | B4: Partially Paid | C4: Completed | D4: High | E4: Signed | F4: Photography | G4: Vegan | H4: Invitation Sent | I4: Both | J4: Wedding Planner | K4: Cash | M4: Gift Card | N4: 6-9 Months Before | O4: Dessert | P4: Transportation | Q4: 3 | W4: =SUMIF(Budget!$B$6:$B$35,Lists!F4,Budget!$F$6:$F$35) -> 0 | X4: =SUMIF(Budget!$B$6:$B$35,Lists!F4,Budget!$G$6:$G$35) -> 0 | AA4: =IFERROR(LARGE(Budget!$G$6:$G$35,3),"") | AB4: =IFERROR(INDEX(Budget!$D$6:$D$35,MATCH(AA4,Budget!$G$6:$G$35,0)),"") | AC4: =COUNTIF('Guest List'!$I$6:$I$65,Lists!A4) -> 0 | AD4: =COUNTIF('Guest List'!$L$6:$L$65,Lists!G4) -> 0 | AE4: =COUNTIFS('Master Checklist'!$B$6:$B$65,Lists!N4,'Master Checklist'!$H$6:$H$65,"Completed") -> 0 | AF4: =COUNTIFS('Master Checklist'!$B$6:$B$65,Lists!N4)-AE4 -> 0 | AG4: 6-9 Months
A5: Tentative | B5: Paid in Full | C5: Overdue | E5: Cancelled | F5: Videography | G5: Gluten-Free | J5: Both | K5: Cheque | M5: Experience | N5: 3-6 Months Before | O5: Cake | P5: Food | Q5: 4 | W5: =SUMIF(Budget!$B$6:$B$35,Lists!F5,Budget!$F$6:$F$35) -> 0 | X5: =SUMIF(Budget!$B$6:$B$35,Lists!F5,Budget!$G$6:$G$35) -> 0 | AA5: =IFERROR(LARGE(Budget!$G$6:$G$35,4),"") | AB5: =IFERROR(INDEX(Budget!$D$6:$D$35,MATCH(AA5,Budget!$G$6:$G$35,0)),"") | AC5: =COUNTIF('Guest List'!$I$6:$I$65,Lists!A5) -> 0 | AD5: =COUNTIF('Guest List'!$L$6:$L$65,Lists!G5) -> 0 | AE5: =COUNTIFS('Master Checklist'!$B$6:$B$65,Lists!N5,'Master Checklist'!$H$6:$H$65,"Completed") -> 0 | AF5: =COUNTIFS('Master Checklist'!$B$6:$B$65,Lists!N5)-AE5 -> 0 | AG5: 3-6 Months
B6: Overdue | F6: Attire | G6: Kids Meal | J6: Parents | K6: Digital Wallet | M6: Registry Item | N6: 1-3 Months Before | O6: Drinks | P6: Activities | Q6: 5 | W6: =SUMIF(Budget!$B$6:$B$35,Lists!F6,Budget!$F$6:$F$35) -> 0 | X6: =SUMIF(Budget!$B$6:$B$35,Lists!F6,Budget!$G$6:$G$35) -> 0 | AA6: =IFERROR(LARGE(Budget!$G$6:$G$35,5),"") | AB6: =IFERROR(INDEX(Budget!$D$6:$D$35,MATCH(AA6,Budget!$G$6:$G$35,0)),"") | AD6: =COUNTIF('Guest List'!$L$6:$L$65,Lists!G6) -> 0 | AE6: =COUNTIFS('Master Checklist'!$B$6:$B$65,Lists!N6,'Master Checklist'!$H$6:$H$65,"Completed") -> 0 | AF6: =COUNTIFS('Master Checklist'!$B$6:$B$65,Lists!N6)-AE6 -> 0 | AG6: 1-3 Months
F7: Beauty | G7: Other | N7: Final Month | O7: Late Night Food | P7: Shopping | W7: =SUMIF(Budget!$B$6:$B$35,Lists!F7,Budget!$F$6:$F$35) -> 0 | X7: =SUMIF(Budget!$B$6:$B$35,Lists!F7,Budget!$G$6:$G$35) -> 0 | AD7: =COUNTIF('Guest List'!$L$6:$L$65,Lists!G7) -> 0 | AE7: =COUNTIFS('Master Checklist'!$B$6:$B$65,Lists!N7,'Master Checklist'!$H$6:$H$65,"Completed") -> 0 | AF7: =COUNTIFS('Master Checklist'!$B$6:$B$65,Lists!N7)-AE7 -> 0 | AG7: Final Month
F8: Flowers | N8: Wedding Week | P8: Travel Insurance | W8: =SUMIF(Budget!$B$6:$B$35,Lists!F8,Budget!$F$6:$F$35) -> 0 | X8: =SUMIF(Budget!$B$6:$B$35,Lists!F8,Budget!$G$6:$G$35) -> 0 | AE8: =COUNTIFS('Master Checklist'!$B$6:$B$65,Lists!N8,'Master Checklist'!$H$6:$H$65,"Completed") -> 0 | AF8: =COUNTIFS('Master Checklist'!$B$6:$B$65,Lists!N8)-AE8 -> 0 | AG8: Wedding Week
F9: Decor | N9: Wedding Day | P9: Miscellaneous | W9: =SUMIF(Budget!$B$6:$B$35,Lists!F9,Budget!$F$6:$F$35) -> 0 | X9: =SUMIF(Budget!$B$6:$B$35,Lists!F9,Budget!$G$6:$G$35) -> 0 | AE9: =COUNTIFS('Master Checklist'!$B$6:$B$65,Lists!N9,'Master Checklist'!$H$6:$H$65,"Completed") -> 0 | AF9: =COUNTIFS('Master Checklist'!$B$6:$B$65,Lists!N9)-AE9 -> 0 | AG9: Wedding Day
F10: Entertainment | N10: Post-Wedding | W10: =SUMIF(Budget!$B$6:$B$35,Lists!F10,Budget!$F$6:$F$35) -> 0 | X10: =SUMIF(Budget!$B$6:$B$35,Lists!F10,Budget!$G$6:$G$35) -> 0 | AE10: =COUNTIFS('Master Checklist'!$B$6:$B$65,Lists!N10,'Master Checklist'!$H$6:$H$65,"Completed") -> 0 | AF10: =COUNTIFS('Master Checklist'!$B$6:$B$65,Lists!N10)-AE10 -> 0 | AG10: Post-Wedding
F11: Music | W11: =SUMIF(Budget!$B$6:$B$35,Lists!F11,Budget!$F$6:$F$35) -> 0 | X11: =SUMIF(Budget!$B$6:$B$35,Lists!F11,Budget!$G$6:$G$35) -> 0
F12: Transportation | W12: =SUMIF(Budget!$B$6:$B$35,Lists!F12,Budget!$F$6:$F$35) -> 0 | X12: =SUMIF(Budget!$B$6:$B$35,Lists!F12,Budget!$G$6:$G$35) -> 0
F13: Invitations | W13: =SUMIF(Budget!$B$6:$B$35,Lists!F13,Budget!$F$6:$F$35) -> 0 | X13: =SUMIF(Budget!$B$6:$B$35,Lists!F13,Budget!$G$6:$G$35) -> 0
F14: Stationery | W14: =SUMIF(Budget!$B$6:$B$35,Lists!F14,Budget!$F$6:$F$35) -> 0 | X14: =SUMIF(Budget!$B$6:$B$35,Lists!F14,Budget!$G$6:$G$35) -> 0
F15: Cake | W15: =SUMIF(Budget!$B$6:$B$35,Lists!F15,Budget!$F$6:$F$35) -> 0 | X15: =SUMIF(Budget!$B$6:$B$35,Lists!F15,Budget!$G$6:$G$35) -> 0
F16: Rings | W16: =SUMIF(Budget!$B$6:$B$35,Lists!F16,Budget!$F$6:$F$35) -> 0 | X16: =SUMIF(Budget!$B$6:$B$35,Lists!F16,Budget!$G$6:$G$35) -> 0
F17: Rentals | W17: =SUMIF(Budget!$B$6:$B$35,Lists!F17,Budget!$F$6:$F$35) -> 0 | X17: =SUMIF(Budget!$B$6:$B$35,Lists!F17,Budget!$G$6:$G$35) -> 0
F18: Accommodation | W18: =SUMIF(Budget!$B$6:$B$35,Lists!F18,Budget!$F$6:$F$35) -> 0 | X18: =SUMIF(Budget!$B$6:$B$35,Lists!F18,Budget!$G$6:$G$35) -> 0
F19: Gifts | W19: =SUMIF(Budget!$B$6:$B$35,Lists!F19,Budget!$F$6:$F$35) -> 0 | X19: =SUMIF(Budget!$B$6:$B$35,Lists!F19,Budget!$G$6:$G$35) -> 0
F20: Honeymoon | W20: =SUMIF(Budget!$B$6:$B$35,Lists!F20,Budget!$F$6:$F$35) -> 0 | X20: =SUMIF(Budget!$B$6:$B$35,Lists!F20,Budget!$G$6:$G$35) -> 0
F21: Miscellaneous | W21: =SUMIF(Budget!$B$6:$B$35,Lists!F21,Budget!$F$6:$F$35) -> 0 | X21: =SUMIF(Budget!$B$6:$B$35,Lists!F21,Budget!$G$6:$G$35) -> 0
